ai_kit/.env.example
ai_kit/__init__.py
ai_kit/cli/__init__.py
ai_kit/cli/cli.py
ai_kit/cli/commands/agent/research.py
ai_kit/cli/commands/env.py
ai_kit/cli/commands/gitingest.py
ai_kit/cli/commands/help.py
ai_kit/cli/commands/init.py
ai_kit/cli/commands/models.py
ai_kit/cli/commands/think.py
ai_kit/cli/commands/web/__init__.py
ai_kit/cli/commands/web/crawl.py
ai_kit/cli/commands/web/fetch.py
ai_kit/cli/commands/web/search.py
ai_kit/cli/registry.py
ai_kit/cli/teammates/__init__.py
ai_kit/cli/teammates/clyde.py
ai_kit/cli/templating.py
ai_kit/config/__init__.py
ai_kit/config/client_config.py
ai_kit/config/openrouter_config.py
ai_kit/core/agents/core.py
ai_kit/core/agents/research.py
ai_kit/core/agents/tools.py
ai_kit/core/agents/utils.py
ai_kit/core/crawler.py
ai_kit/core/llms/client.py
ai_kit/core/llms/cohere_client.py
ai_kit/core/llms/google_genai_client.py
ai_kit/core/llms/groq_client.py
ai_kit/core/llms/openrouter_client.py
ai_kit/core/llms/perplexity_client.py
ai_kit/core/llms/together_client.py
ai_kit/core/next_action.py
ai_kit/core/prompt_loader.py
ai_kit/core/recommender.py
ai_kit/core/router.py
ai_kit/core/web/duckduckgo.py
ai_kit/core/web/fetcher.py
ai_kit/core/web/firecrawl_client.py
ai_kit/core/web/parser.py
ai_kit/core/web/url_processor.py
ai_kit/scripts/publish.py
ai_kit/scripts/teammate_colors.py
ai_kit/shared_console.py
ai_kit/system_prompts/agent/default.md
ai_kit/system_prompts/agent/query_augmentation.md
ai_kit/system_prompts/beta.md
ai_kit/system_prompts/cursorrules/ai-kit.mdc
ai_kit/system_prompts/router.md
ai_kit/system_prompts/teammates/clyde.md
ai_kit/utils/__init__.py
ai_kit/utils/chunker.py
ai_kit/utils/dynamic_file_loader.py
ai_kit/utils/fs.py
ai_kit/utils/logging.py
ai_kit/utils/tokens.py
python_ai_kit-0.15.1.dist-info/METADATA
python_ai_kit-0.15.1.dist-info/WHEEL
python_ai_kit-0.15.1.dist-info/entry_points.txt
python_ai_kit-0.15.1.dist-info/RECORD
