Metadata-Version: 2.3
Name: python-ai-kit
Version: 0.15.1
Summary: AI Kit is a CLI meant to augment your IDE agent.
Author: Ben Everman
Author-email: ben@beneverman.com
Requires-Python: >=3.10,<4.0
Classifier: Programming Language :: Python :: 3
Classifier: Programming Language :: Python :: 3.10
Classifier: Programming Language :: Python :: 3.11
Classifier: Programming Language :: Python :: 3.12
Classifier: Programming Language :: Python :: 3.13
Requires-Dist: aiohttp (>=3.11.11,<4.0.0)
Requires-Dist: anthropic (>=0.49.0,<0.50.0)
Requires-Dist: bs4 (>=0.0.2,<0.0.3)
Requires-Dist: build (>=1.2.2.post1,<2.0.0)
Requires-Dist: chardet (>=5.2.0,<6.0.0)
Requires-Dist: click (>=8.1.8,<9.0.0)
Requires-Dist: cohere (>=5.13.12,<6.0.0)
Requires-Dist: duckduckgo-search (>=7.2.1,<8.0.0)
Requires-Dist: gitingest (>=0.1.3,<0.2.0)
Requires-Dist: google-genai (>=0.6.0,<0.7.0)
Requires-Dist: groq (>=0.18.0,<0.19.0)
Requires-Dist: litellm (>=1.59.6,<2.0.0)
Requires-Dist: markdownify (>=0.14.1,<0.15.0)
Requires-Dist: mistralai (>=1.5.0,<2.0.0)
Requires-Dist: openai (>=1.60.1,<2.0.0)
Requires-Dist: puremagic (>=1.28,<2.0)
Requires-Dist: pydantic (>=2.10.6,<3.0.0)
Requires-Dist: pygithub (>=2.5.0,<3.0.0)
Requires-Dist: pymupdf (>=1.25.3,<2.0.0)
Requires-Dist: pypdf (>=5.2.0,<6.0.0)
Requires-Dist: pytest-mock (>=3.14.0,<4.0.0)
Requires-Dist: python-dotenv (>=1.0.1,<2.0.0)
Requires-Dist: rank-bm25 (>=0.2.2,<0.3.0)
Requires-Dist: rich (>=13.9.4,<14.0.0)
Requires-Dist: tiktoken (>=0.8.0,<0.9.0)
Requires-Dist: together (>=1.3.14,<2.0.0)
Requires-Dist: tomli (>=2.2.1,<3.0.0)
Requires-Dist: twine (>=6.1.0,<7.0.0)
